alchemy_connector/__init__.py
alchemy_connector/alchemy_connector.py
alchemy_connector/sqlalchemy_ssh.py
sqlalchemy_connector-0.1.43.dist-info/METADATA
sqlalchemy_connector-0.1.43.dist-info/WHEEL
sqlalchemy_connector-0.1.43.dist-info/top_level.txt
sqlalchemy_connector-0.1.43.dist-info/RECORD
