Metadata-Version: 2.1
Name: sqlalchemy-connector
Version: 0.1.43
Summary: Python library to connect to SQLAlchemy with SSH Tunnel
Home-page: https://github.com/pualien/py-sqlalchemy-ssh-connector
Author: Matteo Senardi
Author-email: pualien@gmail.com
License: MIT
Classifier: License :: OSI Approved :: MIT License
Classifier: Operating System :: OS Independent
Classifier: Programming Language :: Python :: 3.6
Classifier: Programming Language :: Python :: 3.7
Classifier: Programming Language :: Python :: 3.8
Classifier: Programming Language :: Python :: 3.9
Classifier: Programming Language :: Python :: 3.10
Classifier: Topic :: Software Development :: Libraries :: Application Frameworks
Classifier: Topic :: Software Development :: Libraries :: Python Modules
Requires-Python: ~=3.6
Requires-Dist: pandas >=0.25.3
Requires-Dist: sqlalchemy >=1.4.49
Requires-Dist: PyMySQL ==1.1.0
Requires-Dist: PyYAML ==6.0.1
Requires-Dist: sshtunnel ==0.4.0
Requires-Dist: retry ==0.9.2
Requires-Dist: cryptography >=41.0.4
